Workbook

Sheet Summary
A1: HumanAI Concierge — Client Tracker
A2: Live summary — updates automatically from the other tabs. Example rows (grey italic) are included in counts; delete them when you start.
A4: Clients
A5: Total clients | B5: =COUNTA(Clients!A2:A301) -> 1
A6: Clients with consent signed | B6: =COUNTIF(Clients!I2:I301,"Yes") -> 1
A7: Requests
A8: New enquiries | B8: =COUNTIF(Requests!G2:G301,"New enquiry") -> 0
A9: Quotes waiting for approval | B9: =COUNTIF(Requests!G2:G301,"Quote sent") -> 0
A10: In progress | B10: =COUNTIF(Requests!G2:G301,"In progress")+COUNTIF(Requests!G2:G301,"Approved") -> 0
A11: Done | B11: =COUNTIF(Requests!G2:G301,"Done") -> 1
A12: Overdue (past due date, not done) | B12: =SUMPRODUCT((Requests!J2:J301<>"")*(Requests!J2:J301<TODAY())*(Requests!G2:G301<>"Done")*(Requests!G2:G301<>"Cancelled")) -> 0
A13: Money
A14: Total invoiced incl. GST (₹) | B14: =SUM(Payments!G2:G301) -> 1770
A15: Received (₹) | B15: =SUMIFS(Payments!G2:G301,Payments!I2:I301,"Paid") -> 1770
A16: Pending (₹) | B16: =SUMIFS(Payments!G2:G301,Payments!I2:I301,"Pending") -> 0
A17: Renewals
A18: Renewals due in next 14 days | B18: =SUMPRODUCT((Renewals!F2:F301<>"")*(Renewals!F2:F301<=14)*(Renewals!G2:G301<>"Yes")) -> 0
A20: How to use
A21: 1. Add each new client on the Clients tab (Client ID like HAC-C-002). Tick consent only after the consent form is signed.
A22: 2. Log every request on the Requests tab with its status. Overdue rows turn red.
A23: 3. Record invoices and payments on the Payments tab. GST is calculated from the rate in Payments!N1 (yellow cell — confirm with your CA).
A24: 4. Add insurance/vehicle/passport/property-tax dates on the Renewals tab. Rows due within 14 days turn yellow.
A25: 5. Grey italic row 2 on each tab is an example — overwrite or delete it.
A26: 6. Keep this file private (Google Drive, shared only with partners). It contains personal data — delete client data after the 'Delete data after' date.
A27: Tip: upload to Google Drive and open with Google Sheets to use it on your phone.

Sheet Clients
A1: Client ID | B1: Name | C1: Phone / WhatsApp | D1: Email | E1: City, country | F1: Language | G1: Family member helped (name, relation) | H1: Their address (Bengaluru) | I1: Consent form signed? | J1: Consent date | K1: Plan | L1: Source | M1: Preferences / notes | N1: Delete data after
A2: HAC-C-001 | B2: Example: Ravi Kumar | C2: +1 555 010 0000 | D2: ravi@example.com | E2: Dallas, USA | F2: Kannada | G2: Mother – Sharada (amma) | H2: Jayanagar 4th Block | I2: Yes | J2: 46300 | K2: Monthly plan | L2: Friend/family | M2: Prefers morning visits; Apollo Clinic | N2: =IF(J2="","",DATE(YEAR(J2)+1,MONTH(J2),DAY(J2))) -> 46665
N3: =IF(J3="","",DATE(YEAR(J3)+1,MONTH(J3),DAY(J3)))
N4: =IF(J4="","",DATE(YEAR(J4)+1,MONTH(J4),DAY(J4)))
N5: =IF(J5="","",DATE(YEAR(J5)+1,MONTH(J5),DAY(J5)))
N6: =IF(J6="","",DATE(YEAR(J6)+1,MONTH(J6),DAY(J6)))
N7: =IF(J7="","",DATE(YEAR(J7)+1,MONTH(J7),DAY(J7)))
N8: =IF(J8="","",DATE(YEAR(J8)+1,MONTH(J8),DAY(J8)))
N9: =IF(J9="","",DATE(YEAR(J9)+1,MONTH(J9),DAY(J9)))
N10: =IF(J10="","",DATE(YEAR(J10)+1,MONTH(J10),DAY(J10)))
N11: =IF(J11="","",DATE(YEAR(J11)+1,MONTH(J11),DAY(J11)))
N12: =IF(J12="","",DATE(YEAR(J12)+1,MONTH(J12),DAY(J12)))
N13: =IF(J13="","",DATE(YEAR(J13)+1,MONTH(J13),DAY(J13)))
N14: =IF(J14="","",DATE(YEAR(J14)+1,MONTH(J14),DAY(J14)))
... N301: =IF(J301="","",DATE(YEAR(J301)+1,MONTH(J301),DAY(J301)))

Sheet Requests
A1: Request ID | B1: Date | C1: Client ID | D1: Client name | E1: Service | F1: What was asked | G1: Status | H1: Quote (₹) | I1: Third-party cost (₹) | J1: Due date | K1: Done date | L1: Summary sent? | M1: Notes
A2: HAC-R-001 | B2: 46300 | C2: HAC-C-001 | D2: =IF(C2="","",IFERROR(INDEX(Clients!$B:$B,MATCH(C2,Clients!$A:$A,0)),"Check client ID")) -> Example: Ravi Kumar | E2: NRI Family Care | F2: Accompany amma to cardiology follow-up | G2: Done | H2: 1500 | I2: 450 | J2: 46302 | K2: 46302 | L2: Yes | M2: Cab + consultation receipts shared
D3: =IF(C3="","",IFERROR(INDEX(Clients!$B:$B,MATCH(C3,Clients!$A:$A,0)),"Check client ID"))
D4: =IF(C4="","",IFERROR(INDEX(Clients!$B:$B,MATCH(C4,Clients!$A:$A,0)),"Check client ID"))
D5: =IF(C5="","",IFERROR(INDEX(Clients!$B:$B,MATCH(C5,Clients!$A:$A,0)),"Check client ID"))
D6: =IF(C6="","",IFERROR(INDEX(Clients!$B:$B,MATCH(C6,Clients!$A:$A,0)),"Check client ID"))
D7: =IF(C7="","",IFERROR(INDEX(Clients!$B:$B,MATCH(C7,Clients!$A:$A,0)),"Check client ID"))
D8: =IF(C8="","",IFERROR(INDEX(Clients!$B:$B,MATCH(C8,Clients!$A:$A,0)),"Check client ID"))
D9: =IF(C9="","",IFERROR(INDEX(Clients!$B:$B,MATCH(C9,Clients!$A:$A,0)),"Check client ID"))
D10: =IF(C10="","",IFERROR(INDEX(Clients!$B:$B,MATCH(C10,Clients!$A:$A,0)),"Check client ID"))
D11: =IF(C11="","",IFERROR(INDEX(Clients!$B:$B,MATCH(C11,Clients!$A:$A,0)),"Check client ID"))
D12: =IF(C12="","",IFERROR(INDEX(Clients!$B:$B,MATCH(C12,Clients!$A:$A,0)),"Check client ID"))
D13: =IF(C13="","",IFERROR(INDEX(Clients!$B:$B,MATCH(C13,Clients!$A:$A,0)),"Check client ID"))
D14: =IF(C14="","",IFERROR(INDEX(Clients!$B:$B,MATCH(C14,Clients!$A:$A,0)),"Check client ID"))
... D301: =IF(C301="","",IFERROR(INDEX(Clients!$B:$B,MATCH(C301,Clients!$A:$A,0)),"Check client ID"))

Sheet Payments
A1: Invoice no | B1: Date | C1: Request ID | D1: Client ID | E1: Amount (₹) | F1: GST (₹) | G1: Total (₹) | H1: Mode | I1: Status | J1: Paid date | K1: Reference / UTR | M1: GST rate | N1: 0.18
A2: HAC-INV-001 | B2: 46300 | C2: HAC-R-001 | D2: HAC-C-001 | E2: 1500 | F2: =IF(E2="","",ROUND(E2*$N$1,2)) -> 270 | G2: =IF(E2="","",E2+F2) -> 1770 | H2: UPI | I2: Paid | J2: 46300 | K2: UPI ref 123456789 | M2: ← confirm rate with your CA
F3: =IF(E3="","",ROUND(E3*$N$1,2)) | G3: =IF(E3="","",E3+F3)
F4: =IF(E4="","",ROUND(E4*$N$1,2)) | G4: =IF(E4="","",E4+F4)
F5: =IF(E5="","",ROUND(E5*$N$1,2)) | G5: =IF(E5="","",E5+F5)
F6: =IF(E6="","",ROUND(E6*$N$1,2)) | G6: =IF(E6="","",E6+F6)
F7: =IF(E7="","",ROUND(E7*$N$1,2)) | G7: =IF(E7="","",E7+F7)
F8: =IF(E8="","",ROUND(E8*$N$1,2)) | G8: =IF(E8="","",E8+F8)
F9: =IF(E9="","",ROUND(E9*$N$1,2)) | G9: =IF(E9="","",E9+F9)
F10: =IF(E10="","",ROUND(E10*$N$1,2)) | G10: =IF(E10="","",E10+F10)
F11: =IF(E11="","",ROUND(E11*$N$1,2)) | G11: =IF(E11="","",E11+F11)
F12: =IF(E12="","",ROUND(E12*$N$1,2)) | G12: =IF(E12="","",E12+F12)
F13: =IF(E13="","",ROUND(E13*$N$1,2)) | G13: =IF(E13="","",E13+F13)
F14: =IF(E14="","",ROUND(E14*$N$1,2)) | G14: =IF(E14="","",E14+F14)
... F301: =IF(E301="","",ROUND(E301*$N$1,2)) | G301: =IF(E301="","",E301+F301)

Sheet Renewals
A1: Client ID | B1: Client name | C1: What renews | D1: Due date | E1: Remind on | F1: Days left | G1: Done?
A2: HAC-C-001 | B2: =IF(A2="","",IFERROR(INDEX(Clients!$B:$B,MATCH(A2,Clients!$A:$A,0)),"Check client ID")) -> Example: Ravi Kumar | C2: Amma's health insurance | D2: 46371 | E2: =IF(D2="","",D2-14) -> 46357 | F2: =IF(D2="","",D2-TODAY()) -> 72 | G2: No
B3: =IF(A3="","",IFERROR(INDEX(Clients!$B:$B,MATCH(A3,Clients!$A:$A,0)),"Check client ID")) | E3: =IF(D3="","",D3-14) | F3: =IF(D3="","",D3-TODAY())
B4: =IF(A4="","",IFERROR(INDEX(Clients!$B:$B,MATCH(A4,Clients!$A:$A,0)),"Check client ID")) | E4: =IF(D4="","",D4-14) | F4: =IF(D4="","",D4-TODAY())
B5: =IF(A5="","",IFERROR(INDEX(Clients!$B:$B,MATCH(A5,Clients!$A:$A,0)),"Check client ID")) | E5: =IF(D5="","",D5-14) | F5: =IF(D5="","",D5-TODAY())
B6: =IF(A6="","",IFERROR(INDEX(Clients!$B:$B,MATCH(A6,Clients!$A:$A,0)),"Check client ID")) | E6: =IF(D6="","",D6-14) | F6: =IF(D6="","",D6-TODAY())
B7: =IF(A7="","",IFERROR(INDEX(Clients!$B:$B,MATCH(A7,Clients!$A:$A,0)),"Check client ID")) | E7: =IF(D7="","",D7-14) | F7: =IF(D7="","",D7-TODAY())
B8: =IF(A8="","",IFERROR(INDEX(Clients!$B:$B,MATCH(A8,Clients!$A:$A,0)),"Check client ID")) | E8: =IF(D8="","",D8-14) | F8: =IF(D8="","",D8-TODAY())
B9: =IF(A9="","",IFERROR(INDEX(Clients!$B:$B,MATCH(A9,Clients!$A:$A,0)),"Check client ID")) | E9: =IF(D9="","",D9-14) | F9: =IF(D9="","",D9-TODAY())
B10: =IF(A10="","",IFERROR(INDEX(Clients!$B:$B,MATCH(A10,Clients!$A:$A,0)),"Check client ID")) | E10: =IF(D10="","",D10-14) | F10: =IF(D10="","",D10-TODAY())
B11: =IF(A11="","",IFERROR(INDEX(Clients!$B:$B,MATCH(A11,Clients!$A:$A,0)),"Check client ID")) | E11: =IF(D11="","",D11-14) | F11: =IF(D11="","",D11-TODAY())
B12: =IF(A12="","",IFERROR(INDEX(Clients!$B:$B,MATCH(A12,Clients!$A:$A,0)),"Check client ID")) | E12: =IF(D12="","",D12-14) | F12: =IF(D12="","",D12-TODAY())
B13: =IF(A13="","",IFERROR(INDEX(Clients!$B:$B,MATCH(A13,Clients!$A:$A,0)),"Check client ID")) | E13: =IF(D13="","",D13-14) | F13: =IF(D13="","",D13-TODAY())
B14: =IF(A14="","",IFERROR(INDEX(Clients!$B:$B,MATCH(A14,Clients!$A:$A,0)),"Check client ID")) | E14: =IF(D14="","",D14-14) | F14: =IF(D14="","",D14-TODAY())
... B301: =IF(A301="","",IFERROR(INDEX(Clients!$B:$B,MATCH(A301,Clients!$A:$A,0)),"Check client ID")) | E301: =IF(D301="","",D301-14) | F301: =IF(D301="","",D301-TODAY())

Sheet Lists
A1: Services | B1: Request status | C1: Payment status | D1: Payment mode | E1: Plan | F1: Language | G1: Yes/No | H1: Source
A2: NRI Family Care | B2: New enquiry | C2: Pending | D2: UPI | E2: Pay per request | F2: English | G2: Yes | H2: Friend/family
A3: NRI Remote Shopping | B3: Quote sent | C3: Paid | D3: Bank transfer | E3: Monthly plan | F3: Kannada | G3: No | H3: WhatsApp group
A4: Coming Home Visit | B4: Approved | C4: Refunded | D4: Payment link | E4: Project | F4: Hindi | H4: Instagram
A5: Personal & Household | B5: In progress | D5: Cash (avoid) | F5: Other | H5: Facebook
A6: Senior Digital Help | B6: Done | H6: LinkedIn
A7: Wedding & Events | B7: Cancelled | H7: Google
A8: Relocation | H8: Website
A9: Property Care | H9: Other
A10: Business Concierge
